bspline_mutual_information/__init__.py
bspline_mutual_information/_version.py
bspline_mutual_information/bspline_mutual_information.py
bspline_mutual_information-1.0.0.dist-info/METADATA
bspline_mutual_information-1.0.0.dist-info/WHEEL
bspline_mutual_information-1.0.0.dist-info/licenses/LICENSE
bspline_mutual_information-1.0.0.dist-info/RECORD
