Metadata-Version: 2.4
Name: bspline-mutual-information
Version: 1.0.0
Summary: B-spline based mutual information estimator
Project-URL: Documentation, https://github.com/pnnl-predictive-phenomics/bspline_mutual_information/blob/main/README.md
Project-URL: Issues, https://github.com/pnnl-predictive-phenomics/bspline_mutual_information/issues
Project-URL: Repository, https://github.com/pnnl-predictive-phenomics/bspline_mutual_information.git
Author-email: Yannick Mahlich <yannick.mahlich@pnnl.gov>
Maintainer-email: Yannick Mahlich <yannick.mahlich@pnnl.gov>
License: 2-clause BSD
License-File: LICENSE
Classifier: Development Status :: 5 - Production/Stable
Classifier: Intended Audience :: Science/Research
Classifier: License :: OSI Approved :: BSD License
Classifier: Natural Language :: English
Classifier: Operating System :: OS Independent
Classifier: Programming Language :: Python :: 3 :: Only
Classifier: Programming Language :: Python :: 3.9
Classifier: Programming Language :: Python :: 3.10
Classifier: Programming Language :: Python :: 3.11
Classifier: Programming Language :: Python :: 3.12
Classifier: Programming Language :: Python :: 3.13
Classifier: Topic :: Scientific/Engineering
Classifier: Topic :: Scientific/Engineering :: Bio-Informatics
Classifier: Topic :: Scientific/Engineering :: Mathematics
Requires-Python: >=3.9
Requires-Dist: numpy>=1.22.0
Requires-Dist: scipy>=1.9.0
